icon.py
pyicon-0.3.1.dist-info/LICENSE
pyicon-0.3.1.dist-info/METADATA
pyicon-0.3.1.dist-info/WHEEL
pyicon-0.3.1.dist-info/entry_points.txt
pyicon-0.3.1.dist-info/top_level.txt
pyicon-0.3.1.dist-info/RECORD
