Metadata-Version: 2.1
Name: pyicon
Version: 0.3.1
License-File: LICENSE
Requires-Dist: click
Requires-Dist: pillow
